kotti_analytics
