Metadata-Version: 1.0
Name: kotti-analytics
Version: 0.2
Summary: Add a Google Analytics widget to your Kotti site
Home-page: http://pypi.python.org/pypi/kotti_analytics
Author: Daniel Newton
Author-email: djpnewton@gmail.com
License: MIT
Keywords: google analytics kotti cms pylons pyramid
Platform: UNKNOWN
Classifier: Programming Language :: Python
Classifier: Framework :: Pylons
Classifier: Topic :: Internet :: WWW/HTTP
Classifier: Topic :: Internet :: WWW/HTTP :: Dynamic Content
Classifier: Topic :: Internet :: WWW/HTTP :: WSGI :: Application
Classifier: License :: OSI Approved :: MIT License
